nijiflow/__init__.py
nijiflow/classifier.py
nijiflow/classifier_test.py
nijiflow/models/nijinet_v1_1.0_224.graphdef.pb
nijiflow-0.1.0.dist-info/DESCRIPTION.rst
nijiflow-0.1.0.dist-info/METADATA
nijiflow-0.1.0.dist-info/RECORD
nijiflow-0.1.0.dist-info/WHEEL
nijiflow-0.1.0.dist-info/metadata.json
nijiflow-0.1.0.dist-info/top_level.txt
